<customlist scriptid="customlist_dz_pm_complexity">
    <name>Companion Governance Level</name>
    <customvalues>
        <customvalue scriptid="val_minimal">
            <value>Minimal</value>
        </customvalue>
        <customvalue scriptid="val_standard">
            <value>Standard</value>
        </customvalue>
        <customvalue scriptid="val_governed">
            <value>Governed</value>
        </customvalue>
        <customvalue scriptid="val_supervised">
            <value>Supervised</value>
        </customvalue>
    </customvalues>
</customlist>
